pytest_lock/__init__.py
pytest_lock/__main__.py
pytest_lock/cache.py
pytest_lock/config.py
pytest_lock/fixture.py
pytest_lock/fixtures/__init__.py
pytest_lock/fixtures/base.py
pytest_lock/fixtures/lock.py
pytest_lock/fixtures/reversed.py
pytest_lock/hooks/__init__.py
pytest_lock/hooks/lock.py
pytest_lock/models/__init__.py
pytest_lock/models/cache/__init__.py
pytest_lock/models/cache/file.py
pytest_lock/models/cache/lock.py
pytest_lock/models/cache/signature.py
pytest_lock/models/cli_argument.py
pytest_lock/models/exceptions.py
pytest_lock/parser_file/__init__.py
pytest_lock/parser_file/base.py
pytest_lock/parser_file/builder.py
pytest_lock/parser_file/json.py
pytest_lock/parser_file/pickle.py
pytest_lock/plugin.py
pytest_lock/typing/__init__.py
pytest_lock/typing/supports_str.py
pytest_lock-1.0.1.dist-info/LICENSE
pytest_lock-1.0.1.dist-info/METADATA
pytest_lock-1.0.1.dist-info/WHEEL
pytest_lock-1.0.1.dist-info/entry_points.txt
pytest_lock-1.0.1.dist-info/RECORD
